autopoiesis_mcp/__init__.py
autopoiesis_mcp/mcp_server.py
autopoiesis_mcp-0.1.2.dist-info/METADATA
autopoiesis_mcp-0.1.2.dist-info/WHEEL
autopoiesis_mcp-0.1.2.dist-info/entry_points.txt
autopoiesis_mcp-0.1.2.dist-info/licenses/LICENSE
autopoiesis_mcp-0.1.2.dist-info/RECORD
