Metadata-Version: 2.4
Name: autopoiesis-mcp
Version: 0.1.2
Summary: Self-maintaining work loop system for Claude. Disingenuousness is death.
License-File: LICENSE
Requires-Python: >=3.10
Requires-Dist: mcp>=1.0.0
